qapp_common/__init__.py
qapp_common/async_tasks/__init__.py
qapp_common/async_tasks/async_task.py
qapp_common/async_tasks/export_circuit_task.py
qapp_common/async_tasks/post_processing_task.py
qapp_common/component/__init__.py
qapp_common/component/backend/__init__.py
qapp_common/component/backend/invocation.py
qapp_common/component/backend/job_fetching.py
qapp_common/component/callback/__init__.py
qapp_common/component/callback/update_job_metadata.py
qapp_common/component/device/__init__.py
qapp_common/component/device/device_selection.py
qapp_common/config/__init__.py
qapp_common/config/logging_config.py
qapp_common/config/thread_config.py
qapp_common/data/__init__.py
qapp_common/data/async_task/__init__.py
qapp_common/data/async_task/circuit_export/__init__.py
qapp_common/data/async_task/circuit_export/backend_holder.py
qapp_common/data/async_task/circuit_export/circuit_holder.py
qapp_common/data/backend/__init__.py
qapp_common/data/backend/backend_information.py
qapp_common/data/callback/__init__.py
qapp_common/data/callback/callback_url.py
qapp_common/data/device/__init__.py
qapp_common/data/device/circuit_running_option.py
qapp_common/data/promise/__init__.py
qapp_common/data/promise/post_processing_promise.py
qapp_common/data/promise/promise.py
qapp_common/data/request/__init__.py
qapp_common/data/request/invocation_request.py
qapp_common/data/request/job_fetching_request.py
qapp_common/data/request/request.py
qapp_common/data/response/__init__.py
qapp_common/data/response/authentication.py
qapp_common/data/response/job_response.py
qapp_common/data/response/project_header.py
qapp_common/enum/__init__.py
qapp_common/enum/base_enum.py
qapp_common/enum/http_header.py
qapp_common/enum/invocation_step.py
qapp_common/enum/media_type.py
qapp_common/enum/processing_unit.py
qapp_common/enum/provider_tag.py
qapp_common/enum/sdk.py
qapp_common/enum/token_type.py
qapp_common/enum/status/__init__.py
qapp_common/enum/status/job_status.py
qapp_common-0.0.10.dist-info/LICENSE
qapp_common-0.0.10.dist-info/METADATA
qapp_common-0.0.10.dist-info/WHEEL
qapp_common-0.0.10.dist-info/top_level.txt
qapp_common-0.0.10.dist-info/RECORD
